redmine_commander/__init__.py
redmine_commander/config.py
redmine_commander/confluence_data.py
redmine_commander/custom_rofi.py
redmine_commander/data.py
redmine_commander/get_issues.py
redmine_commander/main.py
redmine_commander/redmine_data.py
redmine_commander/redmine_lib.py
redmine_commander/skeleton.py
redmine_commander/timetracker.py
redmine_commander/utils.py
redmine_commander-1.0.46.dist-info/AUTHORS.rst
redmine_commander-1.0.46.dist-info/LICENSE.txt
redmine_commander-1.0.46.dist-info/METADATA
redmine_commander-1.0.46.dist-info/WHEEL
redmine_commander-1.0.46.dist-info/entry_points.txt
redmine_commander-1.0.46.dist-info/top_level.txt
redmine_commander-1.0.46.dist-info/RECORD
